imagemergetools/__init__.py
imagemergetools/imagemergetools.py
imagemergetools-1.0.4.dist-info/LICENSE
imagemergetools-1.0.4.dist-info/METADATA
imagemergetools-1.0.4.dist-info/WHEEL
imagemergetools-1.0.4.dist-info/top_level.txt
imagemergetools-1.0.4.dist-info/RECORD
