Metadata-Version: 2.1
Name: imagemergetools
Version: 1.0.4
Summary: Tools for combining images
Home-page: https://github.com/Chenkail/imagemergetools
Author: Chenkai Luo
Author-email: chenkai.luo@gmail.com
License: UNKNOWN
Platform: UNKNOWN
Classifier: Programming Language :: Python :: 3
Classifier: License :: OSI Approved :: GNU General Public License v3 (GPLv3)
Classifier: Operating System :: OS Independent
